rogue_scroll/__about__.py
rogue_scroll/__init__.py
rogue_scroll/__main__.py
rogue_scroll/_scroll.py
rogue_scroll/py.typed
rogue_scroll-0.1.3.dist-info/METADATA
rogue_scroll-0.1.3.dist-info/WHEEL
rogue_scroll-0.1.3.dist-info/entry_points.txt
rogue_scroll-0.1.3.dist-info/RECORD
