Metadata-Version: 2.4
Name: rogue-scroll
Version: 0.1.3
Summary: Generate scroll titles from the game rogue
Project-URL: Repository, https://github.com/jpgoldberg/rogue-scroll.git
Project-URL: Issues, https://github.com/jpgoldberg/rogue-scroll/issues
Project-URL: Documentation, https://jpgoldberg.github.io/rogue-scroll/
Project-URL: Changelog, https://github.com/jpgoldberg/rogue-scroll/blob/main/CHANGELOG.md
Author-email: Jeffrey Goldberg <jeffrey@goldmark.org>
Maintainer-email: Jeffrey Goldberg <jeffrey@goldmark.org>
License-Expression: CC-BY-ND-4.0
Classifier: Development Status :: 4 - Beta
Classifier: Environment :: Console
Classifier: Operating System :: OS Independent
Classifier: Programming Language :: Python :: 3.11
Classifier: Programming Language :: Python :: 3.12
Classifier: Programming Language :: Python :: 3.13
Classifier: Programming Language :: Python :: 3.14
Classifier: Topic :: Games/Entertainment
Classifier: Typing :: Typed
Requires-Python: >=3.10
